arbundler/__init__.py
arbundler/data_item.py
arbundler/signer.py
arbundler/tag.py
arbundler/client/__init__.py
arbundler/client/client.py
arbundler/client/types.py
arbundler/helpers/__init__.py
arbundler/helpers/converters.py
arbundler/helpers/deep_hash.py
arbundler/helpers/hashing.py
arbundler/helpers/serializers.py
arbundler-0.3.0.dist-info/METADATA
arbundler-0.3.0.dist-info/WHEEL
arbundler-0.3.0.dist-info/RECORD
