Metadata-Version: 2.4
Name: arbundler
Version: 0.3.0
Author-email: Yolley <Yolley@users.noreply.github.com>
Requires-Python: <3.14,>=3.11
Requires-Dist: anyio<5,>=4
Requires-Dist: cryptography<46,>=43.0.3
Requires-Dist: httpx<1,>=0
Requires-Dist: msgspec<1.0.0,>=0.18.4
Requires-Dist: pyjwt[crypto]<3,>=2.9.0
